pb_rater_example/__init__.py
pb_rater_example/rater.py
pb_rater_example-1.0.0.dist-info/LICENSE
pb_rater_example-1.0.0.dist-info/METADATA
pb_rater_example-1.0.0.dist-info/WHEEL
pb_rater_example-1.0.0.dist-info/top_level.txt
pb_rater_example-1.0.0.dist-info/RECORD
